mmore/__init__.py
mmore/__main__.py
mmore/cli.py
mmore/run_dashboard_backend.py
mmore/run_index.py
mmore/run_index_api.py
mmore/run_live_retrieval.py
mmore/run_postprocess.py
mmore/run_process.py
mmore/run_rag.py
mmore/run_ragcli.py
mmore/run_retriever.py
mmore/run_websearch.py
mmore/type.py
mmore/utils.py
mmore/dashboard/__init__.py
mmore/dashboard/package-lock.json
mmore/dashboard/package.json
mmore/dashboard/backend/__init__.py
mmore/dashboard/backend/client.py
mmore/dashboard/backend/model.py
mmore/dashboard/backend/benchmarks/__init__.py
mmore/dashboard/backend/benchmarks/statistics.py
mmore/dashboard/backend/benchmarks/test_spam.py
mmore/dashboard/frontend/.gitignore
mmore/dashboard/frontend/eslint.config.js
mmore/dashboard/frontend/index.html
mmore/dashboard/frontend/package-lock.json
mmore/dashboard/frontend/package.json
mmore/dashboard/frontend/tsconfig.app.json
mmore/dashboard/frontend/tsconfig.json
mmore/dashboard/frontend/tsconfig.node.json
mmore/dashboard/frontend/vite.config.ts
mmore/dashboard/frontend/public/vite.svg
mmore/dashboard/frontend/src/App.css
mmore/dashboard/frontend/src/App.tsx
mmore/dashboard/frontend/src/GraphAndSublistView.tsx
mmore/dashboard/frontend/src/OverallProgressView.tsx
mmore/dashboard/frontend/src/Progress.ts
mmore/dashboard/frontend/src/Report.ts
mmore/dashboard/frontend/src/ReportsChartView.tsx
mmore/dashboard/frontend/src/ReportsTableView.tsx
mmore/dashboard/frontend/src/WorkerLatest.ts
mmore/dashboard/frontend/src/index.css
mmore/dashboard/frontend/src/main.tsx
mmore/dashboard/frontend/src/vite-env.d.ts
mmore/dashboard/frontend/src/assets/react.svg
mmore/dashboard/node_modules/.package-lock.json
mmore/dashboard/node_modules/safecolor/LICENSE
mmore/dashboard/node_modules/safecolor/README.md
mmore/dashboard/node_modules/safecolor/package.json
mmore/dashboard/node_modules/safecolor/safecolor.js
mmore/index/__init__.py
mmore/index/indexer.py
mmore/process/__init__.py
mmore/process/config.py
mmore/process/crawler.py
mmore-1.1.1.dist-info/licenses/LICENSE
mmore-1.1.1.dist-info/METADATA
mmore-1.1.1.dist-info/WHEEL
mmore-1.1.1.dist-info/entry_points.txt
mmore-1.1.1.dist-info/top_level.txt
mmore-1.1.1.dist-info/RECORD
