Metadata-Version: 2.4
Name: mmore
Version: 1.1.1
Summary: mmore: Scalable multimodal document extraction pipeline for custom RAG integration.
Author-email: Alexandre Sallinen <alexandre.sallinen@epfl.ch>, Paul Teiletche <paul.teiletche@epfl.ch>, Marc-Antoine Allard <marc-antoine.allard@epfl.ch>, Stefan Krsteski <stefan.krsteski@epfl.ch>, David Kalajdzic <david.kalajdzic@epfl.ch>, Michael Zhang <michael.zhang@epfl.ch>, Matthias Meyer <matthias.meyer@sdsc.ethz.ch>, Fabrice Nemo <fabrice.nemo@epfl.ch>, Charlotte Meyer <charlotte.meyer@epfl.ch>, Grieder Lea <lea.grieder@epfl.ch>, Matthew Meyer <matthew.meyer@epfl.ch>, Achille Triomphe <ac
Requires-Python: >=3.10
License-File: LICENSE
Requires-Dist: numpy==1.26.4; python_version < "3.12"
Requires-Dist: numpy==2.2.6; python_version >= "3.12"
Requires-Dist: pandas==2.3.0
Requires-Dist: datasets==4.0.0
Requires-Dist: transformers==4.52.4
Requires-Dist: fasteners==0.19
Requires-Dist: uvicorn==0.34.3
Requires-Dist: python-dotenv==1.0.1
Requires-Dist: dacite==1.8.1
Requires-Dist: click>=8.1.7
Requires-Dist: dask[distributed]>=2025.2.0
Requires-Dist: pytest>=8.3.4
Requires-Dist: httpx==0.28.1
Requires-Dist: Pillow
Requires-Dist: PyMuPDF
Requires-Dist: beautifulsoup4==4.13.4
Requires-Dist: Unidecode
Requires-Dist: clean-text
Requires-Dist: docx2pdf
Requires-Dist: lxml_html_clean
Requires-Dist: python-docx
Requires-Dist: python-pptx
Requires-Dist: clean-text
Requires-Dist: requests==2.32.4
Requires-Dist: selenium==4.34.2
Requires-Dist: surya-ocr>=0.8.3
Requires-Dist: xlrd==2.0.1
Requires-Dist: py7zr==0.22.0
Requires-Dist: rarfile==4.2
Requires-Dist: markdown==3.7
Requires-Dist: markdownify==0.13.1
Requires-Dist: marker-pdf==1.7.5
Requires-Dist: moviepy==2.1.1
Requires-Dist: openpyxl==3.1.5
Requires-Dist: chonkie==0.2.1.post1
Requires-Dist: langdetect>=1.0.9
Requires-Dist: trafilatura==2.0.0
Requires-Dist: datatrove==0.3.0; python_version < "3.12"
Requires-Dist: datatrove==0.6.0; python_version >= "3.12"
Requires-Dist: validators==0.35.0
Requires-Dist: bokeh
Requires-Dist: motor==3.7.1
Requires-Dist: mpmath==1.3.0
Requires-Dist: networkx==3.4.2
Requires-Dist: fastapi[standard]
Requires-Dist: fastapi==0.115.13
Requires-Dist: pydantic==2.11.7
Requires-Dist: pymongo==4.13.2
Requires-Dist: pymilvus==2.5.0
Requires-Dist: milvus-model==0.2.12
Requires-Dist: accelerate==1.7.0
Requires-Dist: cohere==5.15.0
Requires-Dist: langchain-anthropic==0.3.4
Requires-Dist: langchain-aws==0.2.30
Requires-Dist: langchain-cohere==0.4.2
Requires-Dist: langchain_community==0.3.25
Requires-Dist: langchain-huggingface==0.1.2
Requires-Dist: langchain-milvus==0.1.8
Requires-Dist: langchain-mistralai==0.2.7
Requires-Dist: langchain-nvidia-ai-endpoints
Requires-Dist: langchain-openai==0.3.28
Requires-Dist: langchain==0.3.27
Requires-Dist: markdownify==0.13.1
Requires-Dist: ragas==0.3.1
Requires-Dist: nltk>=3.9
Requires-Dist: starlette==0.46
Requires-Dist: typing_extensions==4.14.1
Requires-Dist: sympy==1.14.0
Requires-Dist: google-auth==2.39.0
Requires-Dist: google-api-python-client==2.173.0
Requires-Dist: mammoth==1.9.0
Requires-Dist: argostranslate
Requires-Dist: sentence-transformers
Requires-Dist: langid
Provides-Extra: cpu
Requires-Dist: torch>=2.5.1; extra == "cpu"
Provides-Extra: cu124
Requires-Dist: torch>=2.5.1; extra == "cu124"
Provides-Extra: rag
Requires-Dist: accelerate; extra == "rag"
Requires-Dist: cohere==5.15.0; extra == "rag"
Requires-Dist: langchain-anthropic==0.3.4; extra == "rag"
Requires-Dist: langchain-aws==0.2.30; extra == "rag"
Requires-Dist: langchain-cohere==0.4.2; extra == "rag"
Requires-Dist: langchain-huggingface==0.1.2; extra == "rag"
Requires-Dist: langchain-milvus==0.1.8; extra == "rag"
Requires-Dist: langchain-mistralai==0.2.7; extra == "rag"
Requires-Dist: langchain-nvidia-ai-endpoints; extra == "rag"
Requires-Dist: langchain-openai==0.3.28; extra == "rag"
Requires-Dist: langchain==0.3.27; extra == "rag"
Requires-Dist: langdetect>=1.0.9; extra == "rag"
Requires-Dist: pymilvus==2.5.0; extra == "rag"
Requires-Dist: milvus-model==0.2.12; extra == "rag"
Requires-Dist: ragas==0.3.1; extra == "rag"
Requires-Dist: nltk>=3.9; extra == "rag"
Provides-Extra: dev
Requires-Dist: pytest>=8.0.0; extra == "dev"
Requires-Dist: ruff>=0.4.0; extra == "dev"
Dynamic: license-file
